Metadata-Version: 1.1
Name: Coffin-GaretJax
Version: 0.3.8.dev
Summary: Jinja2 adapter for Django, modified version
Home-page: http://github.com/coffin/coffin
Author: David Cramer
Author-email: dcramer@gmail.com
License: UNKNOWN
Platform: UNKNOWN
Classifier: Framework :: Django
Classifier: Intended Audience :: Developers
Classifier: Intended Audience :: System Administrators
Classifier: Operating System :: OS Independent
Classifier: Topic :: Software Development
